libadctf/__init__.py
libadctf/core.py
libadctf/start_sploit.py
libadctf-0.1.1.dist-info/METADATA
libadctf-0.1.1.dist-info/WHEEL
libadctf-0.1.1.dist-info/entry_points.txt
libadctf-0.1.1.dist-info/licenses/LICENSE
libadctf-0.1.1.dist-info/RECORD
