Metadata-Version: 2.4
Name: libadctf
Version: 0.1.1
Summary: A Python library
License-File: LICENSE
Requires-Python: >=3.9
